{"interviewId":"nominate880","conditions":{"layoutType":"horizontal","tracesDisplayingCondition":"without_traces"},"windowSize":{"height":995,"width":1920},"touchPoints":[{"coordinates":{"x":981,"y":625},"timestamp":1679663011637,"currentPage":"start","triggerId":"start-button"},{"coordinates":{"x":124,"y":178},"timestamp":1679663013775,"currentPage":"product_category","triggerId":"language-button[en]"},{"coordinates":{"x":995,"y":454},"timestamp":1679663026787,"currentPage":"product_category","triggerId":"category-item[1]"},{"coordinates":{"x":288,"y":303},"timestamp":1679663034934,"currentPage":"product_selection","triggerId":"forward-from-selection"},{"coordinates":{"x":120,"y":98},"timestamp":1679663038616,"currentPage":"checkout","triggerId":"navigational-back"},{"coordinates":{"x":267,"y":296},"timestamp":1679663055707,"currentPage":"product_selection","triggerId":"forward-from-selection"},{"coordinates":{"x":253,"y":275},"timestamp":1679663058323,"currentPage":"checkout","triggerId":"navigational-forward"},{"coordinates":{"x":232,"y":280},"timestamp":1679663061555,"currentPage":"payment","triggerId":"finish-round-button"}],"taskNr":1,"cart":[{"title":"Citrus Lemonade 0.5L","amount":1,"entityPrice":1.5}]}