{"interviewId":"prestige268","conditions":{"layoutType":"baseline","tracesDisplayingCondition":"without_traces"},"windowSize":{"height":955,"width":1920},"touchPoints":[{"coordinates":{"x":963,"y":591},"timestamp":1679308341702,"currentPage":"start","triggerId":"start-button"},{"coordinates":{"x":432,"y":324},"timestamp":1679308346846,"currentPage":"product_category","triggerId":"category-item[1]"},{"coordinates":{"x":1652,"y":978},"timestamp":1679308355988,"currentPage":"product_selection","triggerId":"forward-from-selection"},{"coordinates":{"x":1649,"y":964},"timestamp":1679308361230,"currentPage":"checkout","triggerId":"navigational-forward"},{"coordinates":{"x":1755,"y":997},"timestamp":1679308362701,"currentPage":"payment","triggerId":"finish-round-button"}],"taskNr":4,"cart":[{"title":"Citrus Lemonade 0.5L","amount":1,"entityPrice":1.5},{"title":"Cola 0.5L","amount":2,"entityPrice":1.5}]}