{"interviewId":"extreme78","conditions":{"layoutType":"vertical","tracesDisplayingCondition":"with_traces"},"windowSize":{"height":995,"width":1920},"touchPoints":[{"coordinates":{"x":947,"y":590},"timestamp":1679410776238,"currentPage":"start","triggerId":"start-button"},{"coordinates":{"x":166,"y":742},"timestamp":1679410786173,"currentPage":"product_category","triggerId":"language-button[en]"},{"coordinates":{"x":1041,"y":373},"timestamp":1679410789780,"currentPage":"product_category","triggerId":"category-item[1]"},{"coordinates":{"x":1592,"y":1042},"timestamp":1679410801333,"currentPage":"product_selection","triggerId":"forward-from-selection"},{"coordinates":{"x":1626,"y":996},"timestamp":1679410804951,"currentPage":"checkout","triggerId":"navigational-forward"},{"coordinates":{"x":1593,"y":991},"timestamp":1679410806789,"currentPage":"payment","triggerId":"finish-round-button"}],"taskNr":1,"cart":[{"title":"Citrus Lemonade 0.5L","amount":1,"entityPrice":1.5}]}