{"interviewId":"athlete502","conditions":{"layoutType":"horizontal","tracesDisplayingCondition":"with_traces"},"windowSize":{"height":995,"width":1920},"touchPoints":[{"coordinates":{"x":1033,"y":618},"timestamp":1679585407101,"currentPage":"start","triggerId":"start-button"},{"coordinates":{"x":144,"y":177},"timestamp":1679585412868,"currentPage":"product_category","triggerId":"language-button[en]"},{"coordinates":{"x":1029,"y":502},"timestamp":1679585417947,"currentPage":"product_category","triggerId":"category-item[1]"},{"coordinates":{"x":264,"y":284},"timestamp":1679585429072,"currentPage":"product_selection","triggerId":"forward-from-selection"},{"coordinates":{"x":231,"y":310},"timestamp":1679585430707,"currentPage":"checkout","triggerId":"navigational-forward"},{"coordinates":{"x":146,"y":290},"timestamp":1679585434100,"currentPage":"payment","triggerId":"finish-round-button"}],"taskNr":1,"cart":[{"title":"Citrus Lemonade 0.5L","amount":1,"entityPrice":1.5}]}