{"interviewId":"citizen998","conditions":{"layoutType":"baseline","tracesDisplayingCondition":"without_traces"},"windowSize":{"height":995,"width":1920},"touchPoints":[{"coordinates":{"x":930,"y":598},"timestamp":1679668735030,"currentPage":"start","triggerId":"start-button"},{"coordinates":{"x":376,"y":475},"timestamp":1679668736965,"currentPage":"product_category","triggerId":"category-item[1]"},{"coordinates":{"x":1645,"y":966},"timestamp":1679668749517,"currentPage":"product_selection","triggerId":"forward-from-selection"},{"coordinates":{"x":1606,"y":952},"timestamp":1679668756097,"currentPage":"checkout","triggerId":"navigational-forward"},{"coordinates":{"x":1644,"y":962},"timestamp":1679668757336,"currentPage":"payment","triggerId":"finish-round-button"}],"taskNr":4,"cart":[{"title":"Citrus Lemonade 0.5L","amount":1,"entityPrice":1.5},{"title":"Cola 0.5L","amount":2,"entityPrice":1.5}]}