{"interviewId":"minor380","conditions":{"layoutType":"baseline","tracesDisplayingCondition":"with_traces"},"windowSize":{"height":995,"width":1920},"touchPoints":[{"coordinates":{"x":986,"y":688},"timestamp":1679419299954,"currentPage":"start","triggerId":""},{"coordinates":{"x":1006,"y":578},"timestamp":1679419300728,"currentPage":"start","triggerId":"start-button"},{"coordinates":{"x":440,"y":416},"timestamp":1679419302179,"currentPage":"product_category","triggerId":"category-item[1]"},{"coordinates":{"x":1638,"y":823},"timestamp":1679419305671,"currentPage":"product_selection","triggerId":"navigational-backward"},{"coordinates":{"x":1483,"y":753},"timestamp":1679419306537,"currentPage":"product_category","triggerId":"language-button[en]"},{"coordinates":{"x":393,"y":452},"timestamp":1679419310162,"currentPage":"product_category","triggerId":"category-item[1]"},{"coordinates":{"x":1703,"y":962},"timestamp":1679419325576,"currentPage":"product_selection","triggerId":"forward-from-selection"},{"coordinates":{"x":1718,"y":986},"timestamp":1679419326118,"currentPage":"checkout","triggerId":"navigational-forward"},{"coordinates":{"x":1712,"y":979},"timestamp":1679419326649,"currentPage":"payment","triggerId":"finish-round-button"}],"taskNr":3,"cart":[{"title":"Cola 0.5L","amount":2,"entityPrice":1.5},{"title":"Mate Tea 0.33L","amount":1,"entityPrice":2},{"title":"Orange Lemonade 0.5L","amount":1,"entityPrice":1.5}]}