{"interviewId":"athlete502","conditions":{"layoutType":"baseline","tracesDisplayingCondition":"with_traces"},"windowSize":{"height":995,"width":1920},"touchPoints":[{"coordinates":{"x":997,"y":648},"timestamp":1679585749289,"currentPage":"start","triggerId":"start-button"},{"coordinates":{"x":1477,"y":741},"timestamp":1679585752384,"currentPage":"product_category","triggerId":"language-button[en]"},{"coordinates":{"x":408,"y":462},"timestamp":1679585755809,"currentPage":"product_category","triggerId":"category-item[1]"},{"coordinates":{"x":1765,"y":968},"timestamp":1679585763637,"currentPage":"product_selection","triggerId":"forward-from-selection"},{"coordinates":{"x":1773,"y":967},"timestamp":1679585764920,"currentPage":"checkout","triggerId":"navigational-forward"},{"coordinates":{"x":1734,"y":954},"timestamp":1679585767228,"currentPage":"payment","triggerId":"finish-round-button"}],"taskNr":1,"cart":[{"title":"Citrus Lemonade 0.5L","amount":1,"entityPrice":1.5}]}