{"interviewId":"extreme78","conditions":{"layoutType":"vertical","tracesDisplayingCondition":"with_traces"},"windowSize":{"height":995,"width":1920},"touchPoints":[{"coordinates":{"x":1032,"y":587},"timestamp":1679410843865,"currentPage":"start","triggerId":"start-button"},{"coordinates":{"x":136,"y":748},"timestamp":1679410846202,"currentPage":"product_category","triggerId":"language-button[en]"},{"coordinates":{"x":1039,"y":407},"timestamp":1679410848666,"currentPage":"product_category","triggerId":"category-item[1]"},{"coordinates":{"x":1586,"y":990},"timestamp":1679410860174,"currentPage":"product_selection","triggerId":"forward-from-selection"},{"coordinates":{"x":1591,"y":1007},"timestamp":1679410863037,"currentPage":"checkout","triggerId":"navigational-forward"},{"coordinates":{"x":1575,"y":1019},"timestamp":1679410865581,"currentPage":"payment","triggerId":"finish-round-button"}],"taskNr":3,"cart":[{"title":"Cola 0.5L","amount":2,"entityPrice":1.5},{"title":"Mate Tea 0.33L","amount":1,"entityPrice":2},{"title":"Orange Lemonade 0.5L","amount":1,"entityPrice":1.5}]}