{"interviewId":"prestige268","conditions":{"layoutType":"horizontal","tracesDisplayingCondition":"with_traces"},"windowSize":{"height":955,"width":1920},"touchPoints":[{"coordinates":{"x":963,"y":639},"timestamp":1679309088082,"currentPage":"start","triggerId":"start-button"},{"coordinates":{"x":127,"y":174},"timestamp":1679309090873,"currentPage":"product_category","triggerId":"language-button[en]"},{"coordinates":{"x":1039,"y":605},"timestamp":1679309096676,"currentPage":"product_category","triggerId":""},{"coordinates":{"x":1024,"y":286},"timestamp":1679309097594,"currentPage":"product_category","triggerId":"category-item[1]"},{"coordinates":{"x":165,"y":291},"timestamp":1679309112631,"currentPage":"product_selection","triggerId":"forward-from-selection"},{"coordinates":{"x":94,"y":294},"timestamp":1679309115775,"currentPage":"checkout","triggerId":"navigational-forward"},{"coordinates":{"x":251,"y":271},"timestamp":1679309118330,"currentPage":"payment","triggerId":"finish-round-button"}],"taskNr":1,"cart":[{"title":"Citrus Lemonade 0.5L","amount":1,"entityPrice":1.5}]}