{"interviewId":"catch620","conditions":{"layoutType":"vertical","tracesDisplayingCondition":"with_traces"},"windowSize":{"height":995,"width":1920},"touchPoints":[{"coordinates":{"x":986,"y":619},"timestamp":1679672910728,"currentPage":"start","triggerId":"start-button"},{"coordinates":{"x":1019,"y":409},"timestamp":1679672913127,"currentPage":"product_category","triggerId":"category-item[1]"},{"coordinates":{"x":1746,"y":998},"timestamp":1679672926105,"currentPage":"product_selection","triggerId":"forward-from-selection"},{"coordinates":{"x":1567,"y":991},"timestamp":1679672927407,"currentPage":"checkout","triggerId":"navigational-forward"},{"coordinates":{"x":1650,"y":999},"timestamp":1679672928841,"currentPage":"payment","triggerId":"finish-round-button"}],"taskNr":2,"cart":[{"title":"Citrus Lemonade 0.5L","amount":2,"entityPrice":1.5},{"title":"Cola 0.5L","amount":1,"entityPrice":1.5}]}