{"interviewId":"critical1767","conditions":{"layoutType":"baseline","tracesDisplayingCondition":"without_traces"},"windowSize":{"height":955,"width":1920},"touchPoints":[{"coordinates":{"x":990,"y":612},"timestamp":1679323704704,"currentPage":"start","triggerId":"start-button"},{"coordinates":{"x":399,"y":417},"timestamp":1679323707086,"currentPage":"product_category","triggerId":"category-item[1]"},{"coordinates":{"x":1716,"y":969},"timestamp":1679323716609,"currentPage":"product_selection","triggerId":"forward-from-selection"},{"coordinates":{"x":1684,"y":975},"timestamp":1679323717413,"currentPage":"checkout","triggerId":"navigational-forward"},{"coordinates":{"x":1671,"y":1004},"timestamp":1679323719910,"currentPage":"payment","triggerId":"finish-round-button"}],"taskNr":2,"cart":[{"title":"Citrus Lemonade 0.5L","amount":2,"entityPrice":1.5},{"title":"Cola 0.5L","amount":1,"entityPrice":1.5}]}